nyust_sso/__init__.py
nyust_sso/_types.py
nyust_sso/client.py
nyust_sso/errors.py
nyust_sso/tronclass/__init__.py
nyust_sso/tronclass/entity/activity.py
nyust_sso/tronclass/entity/base.py
nyust_sso/tronclass/entity/course.py
nyust_sso/tronclass/utils.py
nyust_sso/utils.py
nyust_sso_client-0.3.0.dist-info/METADATA
nyust_sso_client-0.3.0.dist-info/WHEEL
nyust_sso_client-0.3.0.dist-info/RECORD
